moat/ems/battery/__init__.py
moat/ems/battery/_base.py
moat/ems/battery/_cfg.yaml
moat/ems/battery/_main.py
moat/ems/battery/errors.py
moat/ems/battery/OFF/__init__.py
moat/ems/battery/OFF/_main.py
moat/ems/battery/OFF/dbus.py
moat/ems/battery/conv/steinhart.py
moat/ems/battery/diy_serial/cell.py
moat/ems/battery/diy_serial/comm.py
moat/ems/battery/diy_serial/packet.py
moat_ems_battery-0.2.19.dist-info/licenses/LICENSE.txt
moat_ems_battery-0.2.19.dist-info/METADATA
moat_ems_battery-0.2.19.dist-info/WHEEL
moat_ems_battery-0.2.19.dist-info/top_level.txt
moat_ems_battery-0.2.19.dist-info/RECORD
