Metadata-Version: 2.4
Name: moat-ems-battery
Version: 0.2.19
Summary: REPLACE ME
Author-email: Matthias Urlichs <matthias@urlichs.de>
Project-URL: homepage, https://m-o-a-t.org
Project-URL: repository, https://github.com/M-o-a-T/moat
Keywords: MoaT
Classifier: Development Status :: 4 - Beta
Classifier: Framework :: AnyIO
Classifier: Framework :: Trio
Classifier: Framework :: AsyncIO
Classifier: Programming Language :: Python :: 3
Classifier: Intended Audience :: Developers
Requires-Python: >=3.8
License-File: LICENSE.txt
Requires-Dist: anyio~=4.2
Requires-Dist: msgpack
Requires-Dist: serialpacker
Requires-Dist: pyfuse3
Requires-Dist: moat-util~=0.62.2
Requires-Dist: moat-micro~=0.18.1
Requires-Dist: moat-lib-config~=0.1.1
Requires-Dist: moat-lib-micro~=0.2.1
Requires-Dist: moat-lib-proxy~=0.1.0
Requires-Dist: moat-lib-run~=0.1.1
Requires-Dist: moat-lib-rpc~=0.5.1
Dynamic: license-file
